toku/__init__.py
toku/client.cpython-39-darwin.so
toku/encoders.py
toku/exceptions.py
toku/exponential_backoff.cpython-39-darwin.so
toku/opcodes.cpython-39-darwin.so
toku/server.py
toku/socket_session.cpython-39-darwin.so
toku/socket_watcher.cpython-39-darwin.so
toku/stream_handler.cpython-39-darwin.so
toku-0.2.25.dist-info/LICENSE
toku-0.2.25.dist-info/METADATA
toku-0.2.25.dist-info/WHEEL
toku-0.2.25.dist-info/top_level.txt
toku-0.2.25.dist-info/RECORD
